pyresult/__init__.py
pyresult/operators.py
pyresult/result.py
pyresult-1.1.0.dist-info/DESCRIPTION.rst
pyresult-1.1.0.dist-info/METADATA
pyresult-1.1.0.dist-info/RECORD
pyresult-1.1.0.dist-info/WHEEL
pyresult-1.1.0.dist-info/metadata.json
pyresult-1.1.0.dist-info/top_level.txt
