Metadata-Version: 2.0
Name: pyresult
Version: 1.1.0
Summary: A Result pattern for python
Home-page: https://github.com/iodevs/pyresult
Author: Jindrich Kralevic Smitka
Author-email: smitka.j@gmail.com
License: BSD license
Keywords: pyresult
Platform: UNKNOWN
Classifier: Development Status :: 2 - Pre-Alpha
Classifier: Intended Audience :: Developers
Classifier: License :: OSI Approved :: BSD License
Classifier: Natural Language :: English
Classifier: Programming Language :: Python :: 2
Classifier: Programming Language :: Python :: 2.7
Classifier: Programming Language :: Python :: 3
Classifier: Programming Language :: Python :: 3.3
Classifier: Programming Language :: Python :: 3.4
Classifier: Programming Language :: Python :: 3.5
Requires-Dist: six (>=1.7.3)
Requires-Dist: toolz (>=0.8.2)
